{
    "customerID": "6576-FBXOJ",
    "gender": "Male",
    "SeniorCitizen": "0",
    "Partner": "Yes",
    "Dependents": "No",
    "tenure": "17",
    "PhoneService": "No",
    "MultipleLines": "No phone service",
    "InternetService": "DSL",
    "OnlineSecurity": "No",
    "OnlineBackup": "No",
    "DeviceProtection": "Yes",
    "TechSupport": "Yes",
    "StreamingTV": "Yes",
    "StreamingMovies": "Yes",
    "Contract": "One year",
    "PaperlessBilling": "No",
    "PaymentMethod": "Electronic check",
    "MonthlyCharges": "54.6",
    "TotalCharges": "934.8",
    "Churn": "No"
}