{
    "customerID": "6313-GIDIT",
    "gender": "Male",
    "SeniorCitizen": "1",
    "Partner": "No",
    "Dependents": "No",
    "tenure": "53",
    "PhoneService": "No",
    "MultipleLines": "No phone service",
    "InternetService": "DSL",
    "OnlineSecurity": "No",
    "OnlineBackup": "Yes",
    "DeviceProtection": "Yes",
    "TechSupport": "No",
    "StreamingTV": "Yes",
    "StreamingMovies": "Yes",
    "Contract": "Month-to-month",
    "PaperlessBilling": "Yes",
    "PaymentMethod": "Electronic check",
    "MonthlyCharges": "54.45",
    "TotalCharges": "2854.55",
    "Churn": "Yes"
}