{
    "customerID": "2027-FECZV",
    "gender": "Male",
    "SeniorCitizen": "0",
    "Partner": "No",
    "Dependents": "No",
    "tenure": "12",
    "PhoneService": "Yes",
    "MultipleLines": "Yes",
    "InternetService": "Fiber optic",
    "OnlineSecurity": "No",
    "OnlineBackup": "Yes",
    "DeviceProtection": "Yes",
    "TechSupport": "No",
    "StreamingTV": "Yes",
    "StreamingMovies": "Yes",
    "Contract": "Month-to-month",
    "PaperlessBilling": "Yes",
    "PaymentMethod": "Electronic check",
    "MonthlyCharges": "106.7",
    "TotalCharges": "1253.9",
    "Churn": "Yes"
}