{
    "customerID": "5590-BYNII",
    "gender": "Male",
    "SeniorCitizen": "0",
    "Partner": "No",
    "Dependents": "No",
    "tenure": "22",
    "PhoneService": "Yes",
    "MultipleLines": "Yes",
    "InternetService": "Fiber optic",
    "OnlineSecurity": "Yes",
    "OnlineBackup": "No",
    "DeviceProtection": "No",
    "TechSupport": "No",
    "StreamingTV": "Yes",
    "StreamingMovies": "Yes",
    "Contract": "Month-to-month",
    "PaperlessBilling": "Yes",
    "PaymentMethod": "Electronic check",
    "MonthlyCharges": "100.75",
    "TotalCharges": "2095",
    "Churn": "Yes"
}