{
    "customerID": "3312-UUMZW",
    "gender": "Male",
    "SeniorCitizen": "0",
    "Partner": "Yes",
    "Dependents": "No",
    "tenure": "32",
    "PhoneService": "Yes",
    "MultipleLines": "Yes",
    "InternetService": "Fiber optic",
    "OnlineSecurity": "No",
    "OnlineBackup": "Yes",
    "DeviceProtection": "No",
    "TechSupport": "No",
    "StreamingTV": "Yes",
    "StreamingMovies": "Yes",
    "Contract": "Month-to-month",
    "PaperlessBilling": "Yes",
    "PaymentMethod": "Credit card (automatic)",
    "MonthlyCharges": "98.85",
    "TotalCharges": "3145.9",
    "Churn": "No"
}