{
    "customerID": "7928-VJYAB",
    "gender": "Male",
    "SeniorCitizen": "0",
    "Partner": "Yes",
    "Dependents": "Yes",
    "tenure": "11",
    "PhoneService": "Yes",
    "MultipleLines": "No",
    "InternetService": "Fiber optic",
    "OnlineSecurity": "No",
    "OnlineBackup": "No",
    "DeviceProtection": "No",
    "TechSupport": "No",
    "StreamingTV": "Yes",
    "StreamingMovies": "Yes",
    "Contract": "Month-to-month",
    "PaperlessBilling": "No",
    "PaymentMethod": "Electronic check",
    "MonthlyCharges": "90.6",
    "TotalCharges": "1020.2",
    "Churn": "No"
}