{
    "customerID": "9812-GHVRI",
    "gender": "Female",
    "SeniorCitizen": "0",
    "Partner": "No",
    "Dependents": "No",
    "tenure": "40",
    "PhoneService": "Yes",
    "MultipleLines": "Yes",
    "InternetService": "Fiber optic",
    "OnlineSecurity": "No",
    "OnlineBackup": "No",
    "DeviceProtection": "No",
    "TechSupport": "No",
    "StreamingTV": "No",
    "StreamingMovies": "Yes",
    "Contract": "Month-to-month",
    "PaperlessBilling": "No",
    "PaymentMethod": "Bank transfer (automatic)",
    "MonthlyCharges": "83.85",
    "TotalCharges": "3532.25",
    "Churn": "No"
}