{
    "customerID": "0082-OQIQY",
    "gender": "Male",
    "SeniorCitizen": "0",
    "Partner": "No",
    "Dependents": "No",
    "tenure": "29",
    "PhoneService": "Yes",
    "MultipleLines": "No",
    "InternetService": "Fiber optic",
    "OnlineSecurity": "No",
    "OnlineBackup": "No",
    "DeviceProtection": "No",
    "TechSupport": "Yes",
    "StreamingTV": "Yes",
    "StreamingMovies": "Yes",
    "Contract": "Month-to-month",
    "PaperlessBilling": "Yes",
    "PaymentMethod": "Electronic check",
    "MonthlyCharges": "94.2",
    "TotalCharges": "2607.6",
    "Churn": "No"
}