{
    "customerID": "4323-OHFOW",
    "gender": "Female",
    "SeniorCitizen": "1",
    "Partner": "Yes",
    "Dependents": "No",
    "tenure": "70",
    "PhoneService": "Yes",
    "MultipleLines": "Yes",
    "InternetService": "Fiber optic",
    "OnlineSecurity": "No",
    "OnlineBackup": "Yes",
    "DeviceProtection": "No",
    "TechSupport": "Yes",
    "StreamingTV": "Yes",
    "StreamingMovies": "Yes",
    "Contract": "One year",
    "PaperlessBilling": "Yes",
    "PaymentMethod": "Bank transfer (automatic)",
    "MonthlyCharges": "105.55",
    "TotalCharges": "7195.35",
    "Churn": "No"
}