{
    "customerID": "7881-EVUAD",
    "gender": "Female",
    "SeniorCitizen": "0",
    "Partner": "No",
    "Dependents": "No",
    "tenure": "2",
    "PhoneService": "No",
    "MultipleLines": "No phone service",
    "InternetService": "DSL",
    "OnlineSecurity": "Yes",
    "OnlineBackup": "Yes",
    "DeviceProtection": "No",
    "TechSupport": "No",
    "StreamingTV": "No",
    "StreamingMovies": "Yes",
    "Contract": "Month-to-month",
    "PaperlessBilling": "Yes",
    "PaymentMethod": "Electronic check",
    "MonthlyCharges": "42.6",
    "TotalCharges": "72.4",
    "Churn": "Yes"
}