{
    "customerID": "2237-ZFSMY",
    "gender": "Female",
    "SeniorCitizen": "0",
    "Partner": "No",
    "Dependents": "No",
    "tenure": "39",
    "PhoneService": "Yes",
    "MultipleLines": "No",
    "InternetService": "Fiber optic",
    "OnlineSecurity": "Yes",
    "OnlineBackup": "No",
    "DeviceProtection": "Yes",
    "TechSupport": "Yes",
    "StreamingTV": "Yes",
    "StreamingMovies": "No",
    "Contract": "One year",
    "PaperlessBilling": "Yes",
    "PaymentMethod": "Electronic check",
    "MonthlyCharges": "95.55",
    "TotalCharges": "3692.85",
    "Churn": "Yes"
}