{
    "customerID": "0278-YXOOG",
    "gender": "Male",
    "SeniorCitizen": "0",
    "Partner": "No",
    "Dependents": "No",
    "tenure": "5",
    "PhoneService": "Yes",
    "MultipleLines": "No",
    "InternetService": "No",
    "OnlineSecurity": "No internet service",
    "OnlineBackup": "No internet service",
    "DeviceProtection": "No internet service",
    "TechSupport": "No internet service",
    "StreamingTV": "No internet service",
    "StreamingMovies": "No internet service",
    "Contract": "Month-to-month",
    "PaperlessBilling": "No",
    "PaymentMethod": "Mailed check",
    "MonthlyCharges": "21.05",
    "TotalCharges": "113.85",
    "Churn": "Yes"
}