{
    "customerID": "4193-ORFCL",
    "gender": "Female",
    "SeniorCitizen": "1",
    "Partner": "No",
    "Dependents": "No",
    "tenure": "1",
    "PhoneService": "Yes",
    "MultipleLines": "No",
    "InternetService": "DSL",
    "OnlineSecurity": "No",
    "OnlineBackup": "No",
    "DeviceProtection": "No",
    "TechSupport": "No",
    "StreamingTV": "No",
    "StreamingMovies": "No",
    "Contract": "Month-to-month",
    "PaperlessBilling": "No",
    "PaymentMethod": "Mailed check",
    "MonthlyCharges": "45.1",
    "TotalCharges": "45.1",
    "Churn": "Yes"
}