{
    "customerID": "3255-GRXMG",
    "gender": "Male",
    "SeniorCitizen": "0",
    "Partner": "No",
    "Dependents": "Yes",
    "tenure": "18",
    "PhoneService": "Yes",
    "MultipleLines": "No",
    "InternetService": "DSL",
    "OnlineSecurity": "No",
    "OnlineBackup": "No",
    "DeviceProtection": "No",
    "TechSupport": "No",
    "StreamingTV": "No",
    "StreamingMovies": "No",
    "Contract": "Month-to-month",
    "PaperlessBilling": "Yes",
    "PaymentMethod": "Credit card (automatic)",
    "MonthlyCharges": "45.65",
    "TotalCharges": "747.2",
    "Churn": "No"
}