{
    "customerID": "8433-WPJTV",
    "gender": "Female",
    "SeniorCitizen": "1",
    "Partner": "Yes",
    "Dependents": "Yes",
    "tenure": "65",
    "PhoneService": "Yes",
    "MultipleLines": "Yes",
    "InternetService": "Fiber optic",
    "OnlineSecurity": "No",
    "OnlineBackup": "No",
    "DeviceProtection": "Yes",
    "TechSupport": "Yes",
    "StreamingTV": "Yes",
    "StreamingMovies": "Yes",
    "Contract": "One year",
    "PaperlessBilling": "Yes",
    "PaymentMethod": "Bank transfer (automatic)",
    "MonthlyCharges": "103.9",
    "TotalCharges": "6767.1",
    "Churn": "No"
}