{
    "customerID": "2985-JUUBZ",
    "gender": "Male",
    "SeniorCitizen": "0",
    "Partner": "Yes",
    "Dependents": "Yes",
    "tenure": "40",
    "PhoneService": "Yes",
    "MultipleLines": "Yes",
    "InternetService": "DSL",
    "OnlineSecurity": "No",
    "OnlineBackup": "No",
    "DeviceProtection": "Yes",
    "TechSupport": "No",
    "StreamingTV": "Yes",
    "StreamingMovies": "Yes",
    "Contract": "Month-to-month",
    "PaperlessBilling": "Yes",
    "PaymentMethod": "Electronic check",
    "MonthlyCharges": "74.55",
    "TotalCharges": "3015.75",
    "Churn": "No"
}