{
    "customerID": "2408-WITXK",
    "gender": "Female",
    "SeniorCitizen": "1",
    "Partner": "No",
    "Dependents": "No",
    "tenure": "10",
    "PhoneService": "No",
    "MultipleLines": "No phone service",
    "InternetService": "DSL",
    "OnlineSecurity": "No",
    "OnlineBackup": "No",
    "DeviceProtection": "No",
    "TechSupport": "No",
    "StreamingTV": "No",
    "StreamingMovies": "Yes",
    "Contract": "Month-to-month",
    "PaperlessBilling": "Yes",
    "PaymentMethod": "Electronic check",
    "MonthlyCharges": "34.7",
    "TotalCharges": "329.8",
    "Churn": "Yes"
}