{
    "customerID": "0585-EGDDA",
    "gender": "Male",
    "SeniorCitizen": "0",
    "Partner": "Yes",
    "Dependents": "No",
    "tenure": "40",
    "PhoneService": "Yes",
    "MultipleLines": "No",
    "InternetService": "Fiber optic",
    "OnlineSecurity": "No",
    "OnlineBackup": "Yes",
    "DeviceProtection": "Yes",
    "TechSupport": "No",
    "StreamingTV": "No",
    "StreamingMovies": "No",
    "Contract": "Month-to-month",
    "PaperlessBilling": "Yes",
    "PaymentMethod": "Electronic check",
    "MonthlyCharges": "80",
    "TotalCharges": "3168.75",
    "Churn": "No"
}