{
    "customerID": "2533-QVMSK",
    "gender": "Male",
    "SeniorCitizen": "0",
    "Partner": "Yes",
    "Dependents": "No",
    "tenure": "61",
    "PhoneService": "Yes",
    "MultipleLines": "Yes",
    "InternetService": "Fiber optic",
    "OnlineSecurity": "No",
    "OnlineBackup": "Yes",
    "DeviceProtection": "No",
    "TechSupport": "Yes",
    "StreamingTV": "Yes",
    "StreamingMovies": "No",
    "Contract": "Two year",
    "PaperlessBilling": "Yes",
    "PaymentMethod": "Electronic check",
    "MonthlyCharges": "94.1",
    "TotalCharges": "5638.3",
    "Churn": "Yes"
}