{
    "customerID": "5125-CNDSP",
    "gender": "Male",
    "SeniorCitizen": "0",
    "Partner": "No",
    "Dependents": "Yes",
    "tenure": "63",
    "PhoneService": "No",
    "MultipleLines": "No phone service",
    "InternetService": "DSL",
    "OnlineSecurity": "Yes",
    "OnlineBackup": "Yes",
    "DeviceProtection": "No",
    "TechSupport": "Yes",
    "StreamingTV": "No",
    "StreamingMovies": "No",
    "Contract": "One year",
    "PaperlessBilling": "Yes",
    "PaymentMethod": "Bank transfer (automatic)",
    "MonthlyCharges": "40.6",
    "TotalCharges": "2588.95",
    "Churn": "No"
}