{
    "customerID": "2710-WYVXG",
    "gender": "Female",
    "SeniorCitizen": "0",
    "Partner": "No",
    "Dependents": "No",
    "tenure": "3",
    "PhoneService": "Yes",
    "MultipleLines": "No",
    "InternetService": "DSL",
    "OnlineSecurity": "Yes",
    "OnlineBackup": "Yes",
    "DeviceProtection": "No",
    "TechSupport": "Yes",
    "StreamingTV": "No",
    "StreamingMovies": "Yes",
    "Contract": "Two year",
    "PaperlessBilling": "No",
    "PaymentMethod": "Mailed check",
    "MonthlyCharges": "71.1",
    "TotalCharges": "213.35",
    "Churn": "No"
}