{
    "customerID": "2851-MMUTZ",
    "gender": "Female",
    "SeniorCitizen": "0",
    "Partner": "No",
    "Dependents": "No",
    "tenure": "27",
    "PhoneService": "Yes",
    "MultipleLines": "No",
    "InternetService": "DSL",
    "OnlineSecurity": "No",
    "OnlineBackup": "Yes",
    "DeviceProtection": "No",
    "TechSupport": "Yes",
    "StreamingTV": "No",
    "StreamingMovies": "No",
    "Contract": "Month-to-month",
    "PaperlessBilling": "Yes",
    "PaymentMethod": "Mailed check",
    "MonthlyCharges": "56.15",
    "TotalCharges": "1439.35",
    "Churn": "No"
}